{
	"name": "EMP2240_DelimitedText",
	"properties": {
		"linkedServiceName": {
			"referenceName": "EMP2240_BlobLinkerService",
			"type": "LinkedServiceReference"
		},
		"annotations": [],
		"type": "DelimitedText",
		"typeProperties": {
			"location": {
				"type": "AzureBlobStorageLocation",
				"container": "emp2240"
			},
			"columnDelimiter": ",",
			"escapeChar": "\\",
			"firstRowAsHeader": true,
			"quoteChar": "\""
		},
		"schema": [
			{
				"name": "BranchName",
				"type": "String"
			},
			{
				"name": "EmployeeId",
				"type": "String"
			},
			{
				"name": "Month",
				"type": "String"
			},
			{
				"name": "Salary",
				"type": "String"
			}
		]
	},
	"type": "Microsoft.DataFactory/factories/datasets"
}